README.rst
setup.cfg
setup.py
pyveloedi/__init__.py
pyveloedi/base.py
pyveloedi/veloconnect.py
pyveloedi/winora.py
pyveloedi.egg-info/PKG-INFO
pyveloedi.egg-info/SOURCES.txt
pyveloedi.egg-info/dependency_links.txt
pyveloedi.egg-info/requires.txt
pyveloedi.egg-info/top_level.txt