Metadata-Version: 1.1
Name: pyveloedi
Version: 0.1.0
Summary: Library for communicating with Veloconnect webservices.
Home-page: http://github.com/uvc-ingenieure/pyveloedi
Author: Max Holtzberg
Author-email: mh@uvc.de
License: MIT License
Platform: UNKNOWN
Classifier: Development Status :: 4 - Beta
Classifier: Intended Audience :: Developers
Classifier: License :: OSI Approved :: MIT License
Classifier: Operating System :: OS Independent
Classifier: Programming Language :: Python :: 2
Classifier: Topic :: Software Development :: Libraries :: Python Modules
Classifier: Topic :: Communications
